iiif_image_load/__init__.py
iiif_image_load-0.4.1.dist-info/LICENSE
iiif_image_load-0.4.1.dist-info/METADATA
iiif_image_load-0.4.1.dist-info/WHEEL
iiif_image_load-0.4.1.dist-info/top_level.txt
iiif_image_load-0.4.1.dist-info/RECORD
