Metadata-Version: 2.1
Name: iiif-image-load
Version: 0.4.1
Summary: A python library that loads iiif images (IIIF Image Api Manifests) into a cv2 numpy array
Home-page: https://github.com/Bronson-Brown-deVost/iiif_image_load
Author: Bronson Brown-deVost
Author-email: bronsonbdevost@gmail.com
License: UNKNOWN
Project-URL: Bug Tracker, https://github.com/Bronson-Brown-deVost/iiif_image_load/issues
Platform: UNKNOWN
Classifier: Programming Language :: Python :: 3
Classifier: License :: OSI Approved :: MIT License
Classifier: Operating System :: OS Independent
Requires-Python: >=3.6
License-File: LICENSE
